base58random/__init__.py
base58random-0.0.2.dist-info/LICENSE.txt
base58random-0.0.2.dist-info/METADATA
base58random-0.0.2.dist-info/WHEEL
base58random-0.0.2.dist-info/top_level.txt
base58random-0.0.2.dist-info/RECORD
