Metadata-Version: 2.1
Name: base58random
Version: 0.0.2
Summary: Random base58 generator
Author: Viacheslav Alekseev
Author-email: alexeev.corp@gmail.com
License-File: LICENSE.txt
